{
  "navigation": {
    "home": "Home",
    "about": "About",
    "login": "Sign In",
    "register": "Register"
  },
  "page": {
    "home": {
      "title": "Welcome to NextJs i18n",
      "description": "Internationalization in NextJs 13 App router"
    },
    "about": {
      "title": "About Us",
      "description": "This is the about page"
    },
    "login": {
      "title": "Sign In",
      "email": "Email Address",
      "password": "Password",
      "button": "Sign In",
      "link": "Need help ?"
    },
    "register": {
      "title": "Register",
      "email": "Email Address",
      "password": "Password",
      "button": "Sign Up"
    },
    "password": {
      "title": "Reset the password",
      "email": "Email",
      "button": "Check email address",
      "text": "A link to reset your password has been sent by mail to your address."
    }
  },
  "errors": {
    "login": {
      "required_email": "An email adress is required.",
      "not_valid_email": "Adresse email invalide.",
      "password_required": "A password is required.",
      "not_valid_password": "The password must contain at least 8 characters, one letter, one number, a cap and a special char.",
      "credentials": "Credentials incorrect"
    },
    "password": {
      "required_email": "An email adress is required.",
      "not_valid_email": "Adresse email invalide.",
      "no_user": "User does not exist"
    }
  },
  "responses": {
    "email_verified": "Email verified"
  }
}
